japandeaths.py
japandeaths-0.0.2.dist-info/METADATA
japandeaths-0.0.2.dist-info/WHEEL
japandeaths-0.0.2.dist-info/entry_points.txt
japandeaths-0.0.2.dist-info/top_level.txt
japandeaths-0.0.2.dist-info/RECORD
