Metadata-Version: 2.1
Name: japandeaths
Version: 0.0.2
Summary: Visualization of Japanese number of deaths in Covid-19.
Home-page: https://github.com/i-inose/japandeaths
Author: izuru inose
Author-email: i.inose0304@gmail.com
Project-URL: Bug Tracker, https://github.com/i-inose/japandeaths
Classifier: Programming Language :: Python :: 3
Classifier: License :: OSI Approved :: MIT License
Classifier: Operating System :: OS Independent
Requires-Python: >=3.7
